[{"line":2,"elements":[{"start_timestamp":"2024-11-13T17:30:58.422Z","line":22,"name":"login page offline scenaios","description":"","id":"title-of-your-feature;login-page-offline-scenaios;;2","type":"scenario","keyword":"Scenario Outline","steps":[{"result":{"duration":307613900,"status":"passed"},"line":6,"name":"Navigate to the login page","match":{"location":"sanity_script.step_defination.navigate_to_the_login_page()"},"keyword":"Given "},{"result":{"duration":10323000,"status":"passed"},"line":7,"name":"Goes to offline","match":{"location":"sanity_script.step_defination.goes_to_offline()"},"keyword":"When "},{"result":{"duration":3752000600,"status":"passed"},"line":8,"name":"single \"You are currently offline\" toast is displayed","match":{"arguments":[{"val":"\"You are currently offline\"","offset":7}],"location":"sanity_script.step_defination.single_toast_is_displayed(java.lang.String)"},"keyword":"Then "},{"result":{"duration":52500900,"status":"passed"},"line":9,"name":"click on the singin button without filling the email and password","match":{"location":"sanity_script.step_defination.click_on_the_singin_button_without_filling_the_email_and_password()"},"keyword":"When "},{"result":{"duration":3726585200,"status":"passed"},"line":10,"name":"single \"Please check your internet connection\" toast is displayed","match":{"arguments":[{"val":"\"Please check your internet connection\"","offset":7}],"location":"sanity_script.step_defination.single_toast_is_displayed(java.lang.String)"},"keyword":"Then "},{"result":{"duration":399466700,"status":"passed"},"line":11,"name":"fill with invalid emailID and password click on the signin button","match":{"location":"sanity_script.step_defination.fill_with_invalid_email_id_and_password_click_on_the_signin_button()"},"keyword":"When "},{"result":{"duration":3222056500,"status":"passed"},"line":12,"name":"single \"Please check your internet connection\" toast is displayed","match":{"arguments":[{"val":"\"Please check your internet connection\"","offset":7}],"location":"sanity_script.step_defination.single_toast_is_displayed(java.lang.String)"},"keyword":"Then "},{"result":{"error_message":"org.openqa.selenium.InvalidSelectorException: invalid selector\nfrom javascript error: {\"status\":32,\"value\":\"Unable to locate an element with the xpath expression SuperAdmin!@#$1234 because of the following error:\\nSyntaxError: Failed to execute 'evaluate' on 'Document': The string 'SuperAdmin!@#$1234' is not a valid XPath expression.\"}\n  (Session info: chrome=130.0.6723.117)\nFor documentation on this error, please visit: https://www.selenium.dev/documentation/webdriver/troubleshooting/errors#invalid-selector-exception\nBuild info: version: '4.26.0', revision: '8ccf0219d7'\nSystem info: os.name: 'Windows 11', os.arch: 'amd64', os.version: '10.0', java.version: '21.0.4'\nDriver info: org.openqa.selenium.chrome.ChromeDriver\nCommand: [fae04ea612c8201c3813ca8b7e822f07, findElement {using=xpath, value=SuperAdmin!@#$1234}]\nCapabilities {acceptInsecureCerts: false, browserName: chrome, browserVersion: 130.0.6723.117, chrome: {chromedriverVersion: 130.0.6723.116 (6ac35f94ae3..., userDataDir: C:\\Users\\guru\\AppData\\Local...}, fedcm:accounts: true, goog:chromeOptions: {debuggerAddress: localhost:52674}, networkConnectionEnabled: false, pageLoadStrategy: normal, platformName: windows, proxy: Proxy(), se:cdp: ws://localhost:52674/devtoo..., se:cdpVersion: 130.0.6723.117, setWindowRect: true, strictFileInteractability: false, timeouts: {implicit: 0, pageLoad: 300000, script: 30000}, unhandledPromptBehavior: dismiss and notify, webauthn:extension:credBlob: true, webauthn:extension:largeBlob: true, webauthn:extension:minPinLength: true, webauthn:extension:prf: true, webauthn:virtualAuthenticators: true}\nSession ID: fae04ea612c8201c3813ca8b7e822f07\r\n\tat java.base/jdk.internal.reflect.DirectConstructorHandleAccessor.newInstance(DirectConstructorHandleAccessor.java:62)\r\n\tat java.base/java.lang.reflect.Constructor.newInstanceWithCaller(Constructor.java:502)\r\n\tat java.base/java.lang.reflect.Constructor.newInstance(Constructor.java:486)\r\n\tat org.openqa.selenium.remote.ErrorCodec.decode(ErrorCodec.java:167)\r\n\tat org.openqa.selenium.remote.codec.w3c.W3CHttpResponseCodec.decode(W3CHttpResponseCodec.java:138)\r\n\tat org.openqa.selenium.remote.codec.w3c.W3CHttpResponseCodec.decode(W3CHttpResponseCodec.java:50)\r\n\tat org.openqa.selenium.remote.HttpCommandExecutor.execute(HttpCommandExecutor.java:190)\r\n\tat org.openqa.selenium.remote.service.DriverCommandExecutor.invokeExecute(DriverCommandExecutor.java:216)\r\n\tat org.openqa.selenium.remote.service.DriverCommandExecutor.execute(DriverCommandExecutor.java:174)\r\n\tat org.openqa.selenium.remote.RemoteWebDriver.execute(RemoteWebDriver.java:545)\r\n\tat org.openqa.selenium.remote.ElementLocation$ElementFinder$2.findElement(ElementLocation.java:165)\r\n\tat org.openqa.selenium.remote.ElementLocation.findElement(ElementLocation.java:59)\r\n\tat org.openqa.selenium.remote.RemoteWebDriver.findElement(RemoteWebDriver.java:368)\r\n\tat org.openqa.selenium.remote.RemoteWebDriver.findElement(RemoteWebDriver.java:362)\r\n\tat org.openqa.selenium.support.ui.ExpectedConditions$7.apply(ExpectedConditions.java:194)\r\n\tat org.openqa.selenium.support.ui.ExpectedConditions$7.apply(ExpectedConditions.java:190)\r\n\tat org.openqa.selenium.support.ui.FluentWait.until(FluentWait.java:203)\r\n\tat sanity_script.Runner.online(Runner.java:149)\r\n\tat sanity_script.step_defination.connect_back_to_online(step_defination.java:50)\r\n\tat ✽.connect back to online(file:///C:/Users/guru/Desktop/Automation_script/OTF_script/src/main/java/feature_file/OTF_sanity.feature:17)\r\n","duration":29308900,"status":"failed"},"line":17,"name":"connect back to online","match":{"location":"sanity_script.step_defination.connect_back_to_online()"},"keyword":"When "},{"result":{"status":"skipped"},"line":18,"name":"single \"Connected\" toast is displayed","match":{"arguments":[{"val":"\"Connected\"","offset":7}],"location":"sanity_script.step_defination.single_toast_is_displayed(java.lang.String)"},"keyword":"Then "}],"tags":[{"name":"@tag"},{"name":"@offline"}]},{"start_timestamp":"2024-11-13T17:31:09.947Z","line":25,"name":"Login the application","description":"","id":"title-of-your-feature;login-the-application","type":"scenario","keyword":"Scenario","steps":[{"result":{"duration":385703800,"status":"passed"},"line":26,"name":"Enter the username and password and click on the login the button.","match":{"location":"sanity_script.step_defination.enter_the_username_and_password_and_click_on_the_login_the_button()"},"keyword":"When "},{"result":{"error_message":"java.lang.AssertionError: invalid URL expected [true] but found [false]\r\n\tat org.testng.Assert.fail(Assert.java:99)\r\n\tat org.testng.Assert.failNotEquals(Assert.java:1037)\r\n\tat org.testng.Assert.assertTrue(Assert.java:45)\r\n\tat sanity_script.step_defination.if_login_success_page_should_be_navigating_to_the_stream_page(step_defination.java:60)\r\n\tat ✽.If login success page should be navigating to the stream page.(file:///C:/Users/guru/Desktop/Automation_script/OTF_script/src/main/java/feature_file/OTF_sanity.feature:27)\r\n","duration":10024000,"status":"failed"},"line":27,"name":"If login success page should be navigating to the stream page.","match":{"location":"sanity_script.step_defination.if_login_success_page_should_be_navigating_to_the_stream_page()"},"keyword":"Then "}],"tags":[{"name":"@tag"},{"name":"@sanity"}]},{"start_timestamp":"2024-11-13T17:31:10.355Z","line":71,"name":"Stream page offline scenario.","description":"","id":"title-of-your-feature;stream-page-offline-scenario.;;2","type":"scenario","keyword":"Scenario Outline","steps":[{"result":{"error_message":"org.openqa.selenium.TimeoutException: Expected condition failed: waiting for visibility of element located by By.xpath: (//a[@href='/broadcast'])[2] (tried for 10 second(s) with 500 milliseconds interval)\nBuild info: version: '4.26.0', revision: '8ccf0219d7'\nSystem info: os.name: 'Windows 11', os.arch: 'amd64', os.version: '10.0', java.version: '21.0.4'\nDriver info: org.openqa.selenium.chrome.ChromeDriver\nCapabilities {acceptInsecureCerts: false, browserName: chrome, browserVersion: 130.0.6723.117, chrome: {chromedriverVersion: 130.0.6723.116 (6ac35f94ae3..., userDataDir: C:\\Users\\guru\\AppData\\Local...}, fedcm:accounts: true, goog:chromeOptions: {debuggerAddress: localhost:52674}, networkConnectionEnabled: false, pageLoadStrategy: normal, platformName: windows, proxy: Proxy(), se:cdp: ws://localhost:52674/devtoo..., se:cdpVersion: 130.0.6723.117, setWindowRect: true, strictFileInteractability: false, timeouts: {implicit: 0, pageLoad: 300000, script: 30000}, unhandledPromptBehavior: dismiss and notify, webauthn:extension:credBlob: true, webauthn:extension:largeBlob: true, webauthn:extension:minPinLength: true, webauthn:extension:prf: true, webauthn:virtualAuthenticators: true}\nSession ID: fae04ea612c8201c3813ca8b7e822f07\r\n\tat org.openqa.selenium.support.ui.WebDriverWait.timeoutException(WebDriverWait.java:84)\r\n\tat org.openqa.selenium.support.ui.FluentWait.until(FluentWait.java:228)\r\n\tat sanity_script.step_defination.navigate_to_the_stream_page(step_defination.java:66)\r\n\tat ✽.Navigate to the stream page(file:///C:/Users/guru/Desktop/Automation_script/OTF_script/src/main/java/feature_file/OTF_sanity.feature:31)\r\n","duration":13831507700,"status":"failed"},"line":31,"name":"Navigate to the stream page","match":{"location":"sanity_script.step_defination.navigate_to_the_stream_page()"},"keyword":"Given "},{"result":{"status":"skipped"},"line":32,"name":"Goes to offline","match":{"location":"sanity_script.step_defination.goes_to_offline()"},"keyword":"When "},{"result":{"status":"skipped"},"line":33,"name":"single \"You are currently offline\" toast is displayed","match":{"arguments":[{"val":"\"You are currently offline\"","offset":7}],"location":"sanity_script.step_defination.single_toast_is_displayed(java.lang.String)"},"keyword":"Then "},{"result":{"status":"skipped"},"line":34,"name":"click on the create stream button","match":{"location":"sanity_script.step_defination.click_on_the_create_stream_button()"},"keyword":"When "},{"result":{"status":"skipped"},"line":35,"name":"single \"Please check your internet connection\" toast is displayed","match":{"arguments":[{"val":"\"Please check your internet connection\"","offset":7}],"location":"sanity_script.step_defination.single_toast_is_displayed(java.lang.String)"},"keyword":"Then "},{"result":{"duration":1004000,"status":"skipped"},"line":36,"name":"click on the create Record video button","match":{"location":"sanity_script.step_defination.click_on_the_create_record_video_button()"},"keyword":"When "},{"result":{"status":"skipped"},"line":37,"name":"single \"Please check your internet connection\" toast is displayed","match":{"arguments":[{"val":"\"Please check your internet connection\"","offset":7}],"location":"sanity_script.step_defination.single_toast_is_displayed(java.lang.String)"},"keyword":"Then "},{"result":{"status":"skipped"},"line":38,"name":"click on the Schedule Webinar video button","match":{"location":"sanity_script.step_defination.click_on_the_schedule_webinar_video_button()"},"keyword":"When "},{"result":{"status":"skipped"},"line":39,"name":"single \"Please check your internet connection\" toast is displayed","match":{"arguments":[{"val":"\"Please check your internet connection\"","offset":7}],"location":"sanity_script.step_defination.single_toast_is_displayed(java.lang.String)"},"keyword":"Then "},{"result":{"status":"skipped"},"line":40,"name":"click on the upcoming tab","match":{"location":"sanity_script.step_defination.click_on_the_upcoming_tab()"},"keyword":"When "},{"result":{"status":"skipped"},"line":41,"name":"single \"Please check your internet connection\" toast is displayed","match":{"arguments":[{"val":"\"Please check your internet connection\"","offset":7}],"location":"sanity_script.step_defination.single_toast_is_displayed(java.lang.String)"},"keyword":"Then "},{"result":{"status":"skipped"},"line":42,"name":"click on the Past tab","match":{"location":"sanity_script.step_defination.click_on_the_past_tab()"},"keyword":"When "},{"result":{"status":"skipped"},"line":43,"name":"single \"Please check your internet connection\" toast is displayed","match":{"arguments":[{"val":"\"Please check your internet connection\"","offset":7}],"location":"sanity_script.step_defination.single_toast_is_displayed(java.lang.String)"},"keyword":"Then "},{"result":{"status":"skipped"},"line":44,"name":"try to search on the search","match":{"location":"sanity_script.step_defination.try_to_search_on_the_search()"},"keyword":"When "},{"result":{"status":"skipped"},"line":45,"name":"single \"Please check your internet connection\" toast is displayed","match":{"arguments":[{"val":"\"Please check your internet connection\"","offset":7}],"location":"sanity_script.step_defination.single_toast_is_displayed(java.lang.String)"},"keyword":"Then "},{"result":{"status":"skipped"},"line":46,"name":"loader is displayed","match":{"location":"sanity_script.step_defination.loader_is_displayed()"},"keyword":"And "},{"result":{"status":"skipped"},"line":47,"name":"connect back to online","match":{"location":"sanity_script.step_defination.connect_back_to_online()"},"keyword":"When "},{"result":{"status":"skipped"},"line":48,"name":"single \"Connected\" toast is displayed","match":{"arguments":[{"val":"\"Connected\"","offset":7}],"location":"sanity_script.step_defination.single_toast_is_displayed(java.lang.String)"},"keyword":"Then "}],"tags":[{"name":"@tag"},{"name":"@offline"}]},{"start_timestamp":"2024-11-13T17:31:24.198Z","line":83,"name":"Destination page offline scenario","description":"","id":"title-of-your-feature;destination-page-offline-scenario;;2","type":"scenario","keyword":"Scenario Outline","steps":[{"result":{"error_message":"org.openqa.selenium.TimeoutException: Expected condition failed: waiting for visibility of element located by By.xpath: //a[@href='/integration'] (tried for 10 second(s) with 500 milliseconds interval)\r\n\tat org.openqa.selenium.support.ui.WebDriverWait.timeoutException(WebDriverWait.java:84)\r\n\tat org.openqa.selenium.support.ui.FluentWait.until(FluentWait.java:228)\r\n\tat sanity_script.step_defination.navigate_to_the_destination_page_by_click_on_the_destination_menu(step_defination.java:108)\r\n\tat ✽.Navigate to the destination page by click on the destination menu(file:///C:/Users/guru/Desktop/Automation_script/OTF_script/src/main/java/feature_file/OTF_sanity.feature:75)\r\nCaused by: org.openqa.selenium.NoSuchWindowException: no such window: target window already closed\nfrom unknown error: web view not found\n  (Session info: chrome=130.0.6723.117)\nBuild info: version: '4.26.0', revision: '8ccf0219d7'\nSystem info: os.name: 'Windows 11', os.arch: 'amd64', os.version: '10.0', java.version: '21.0.4'\nDriver info: org.openqa.selenium.chrome.ChromeDriver\nCommand: [fae04ea612c8201c3813ca8b7e822f07, findElement {using=xpath, value=//a[@href='/integration']}]\nCapabilities {acceptInsecureCerts: false, browserName: chrome, browserVersion: 130.0.6723.117, chrome: {chromedriverVersion: 130.0.6723.116 (6ac35f94ae3..., userDataDir: C:\\Users\\guru\\AppData\\Local...}, fedcm:accounts: true, goog:chromeOptions: {debuggerAddress: localhost:52674}, networkConnectionEnabled: false, pageLoadStrategy: normal, platformName: windows, proxy: Proxy(), se:cdp: ws://localhost:52674/devtoo..., se:cdpVersion: 130.0.6723.117, setWindowRect: true, strictFileInteractability: false, timeouts: {implicit: 0, pageLoad: 300000, script: 30000}, unhandledPromptBehavior: dismiss and notify, webauthn:extension:credBlob: true, webauthn:extension:largeBlob: true, webauthn:extension:minPinLength: true, webauthn:extension:prf: true, webauthn:virtualAuthenticators: true}\nSession ID: fae04ea612c8201c3813ca8b7e822f07\r\n\tat java.base/jdk.internal.reflect.DirectConstructorHandleAccessor.newInstance(DirectConstructorHandleAccessor.java:62)\r\n\tat java.base/java.lang.reflect.Constructor.newInstanceWithCaller(Constructor.java:502)\r\n\tat java.base/java.lang.reflect.Constructor.newInstance(Constructor.java:486)\r\n\tat org.openqa.selenium.remote.ErrorCodec.decode(ErrorCodec.java:167)\r\n\tat org.openqa.selenium.remote.codec.w3c.W3CHttpResponseCodec.decode(W3CHttpResponseCodec.java:138)\r\n\tat org.openqa.selenium.remote.codec.w3c.W3CHttpResponseCodec.decode(W3CHttpResponseCodec.java:50)\r\n\tat org.openqa.selenium.remote.HttpCommandExecutor.execute(HttpCommandExecutor.java:190)\r\n\tat org.openqa.selenium.remote.service.DriverCommandExecutor.invokeExecute(DriverCommandExecutor.java:216)\r\n\tat org.openqa.selenium.remote.service.DriverCommandExecutor.execute(DriverCommandExecutor.java:174)\r\n\tat org.openqa.selenium.remote.RemoteWebDriver.execute(RemoteWebDriver.java:545)\r\n\tat org.openqa.selenium.remote.ElementLocation$ElementFinder$2.findElement(ElementLocation.java:165)\r\n\tat org.openqa.selenium.remote.ElementLocation.findElement(ElementLocation.java:59)\r\n\tat org.openqa.selenium.remote.RemoteWebDriver.findElement(RemoteWebDriver.java:368)\r\n\tat org.openqa.selenium.remote.RemoteWebDriver.findElement(RemoteWebDriver.java:362)\r\n\tat org.openqa.selenium.support.ui.ExpectedConditions$7.apply(ExpectedConditions.java:194)\r\n\tat org.openqa.selenium.support.ui.ExpectedConditions$7.apply(ExpectedConditions.java:190)\r\n\tat org.openqa.selenium.support.ui.FluentWait.until(FluentWait.java:203)\r\n\tat sanity_script.step_defination.navigate_to_the_destination_page_by_click_on_the_destination_menu(step_defination.java:108)\r\n\tat java.base/jdk.internal.reflect.DirectMethodHandleAccessor.invoke(DirectMethodHandleAccessor.java:103)\r\n\tat java.base/java.lang.reflect.Method.invoke(Method.java:580)\r\n\tat io.cucumber.java.Invoker.doInvoke(Invoker.java:66)\r\n\tat io.cucumber.java.Invoker.invoke(Invoker.java:24)\r\n\tat io.cucumber.java.AbstractGlueDefinition.invokeMethod(AbstractGlueDefinition.java:47)\r\n\tat io.cucumber.java.JavaStepDefinition.execute(JavaStepDefinition.java:29)\r\n\tat io.cucumber.core.runner.CoreStepDefinition.execute(CoreStepDefinition.java:66)\r\n\tat io.cucumber.core.runner.PickleStepDefinitionMatch.runStep(PickleStepDefinitionMatch.java:62)\r\n\tat io.cucumber.core.runner.ExecutionMode$1.execute(ExecutionMode.java:10)\r\n\tat io.cucumber.core.runner.TestStep.executeStep(TestStep.java:81)\r\n\tat io.cucumber.core.runner.TestStep.run(TestStep.java:53)\r\n\tat io.cucumber.core.runner.PickleStepTestStep.run(PickleStepTestStep.java:51)\r\n\tat io.cucumber.core.runner.TestCase.run(TestCase.java:84)\r\n\tat io.cucumber.core.runner.Runner.runPickle(Runner.java:75)\r\n\tat io.cucumber.testng.TestNGCucumberRunner.lambda$runScenario$1(TestNGCucumberRunner.java:135)\r\n\tat io.cucumber.core.runtime.CucumberExecutionContext.lambda$runTestCase$5(CucumberExecutionContext.java:136)\r\n\tat io.cucumber.core.runtime.RethrowingThrowableCollector.executeAndThrow(RethrowingThrowableCollector.java:23)\r\n\tat io.cucumber.core.runtime.CucumberExecutionContext.runTestCase(CucumberExecutionContext.java:136)\r\n\tat io.cucumber.testng.TestNGCucumberRunner.runScenario(TestNGCucumberRunner.java:132)\r\n\tat io.cucumber.testng.AbstractTestNGCucumberTests.runScenario(AbstractTestNGCucumberTests.java:35)\r\n\tat java.base/jdk.internal.reflect.DirectMethodHandleAccessor.invoke(DirectMethodHandleAccessor.java:103)\r\n\tat java.base/java.lang.reflect.Method.invoke(Method.java:580)\r\n\tat org.testng.internal.MethodInvocationHelper.invokeMethod(MethodInvocationHelper.java:133)\r\n\tat org.testng.internal.TestInvoker.invokeMethod(TestInvoker.java:598)\r\n\tat org.testng.internal.TestInvoker.invokeTestMethod(TestInvoker.java:173)\r\n\tat org.testng.internal.MethodRunner.runInSequence(MethodRunner.java:46)\r\n\tat org.testng.internal.TestInvoker$MethodInvocationAgent.invoke(TestInvoker.java:824)\r\n\tat org.testng.internal.TestInvoker.invokeTestMethods(TestInvoker.java:146)\r\n\tat org.testng.internal.TestMethodWorker.invokeTestMethods(TestMethodWorker.java:146)\r\n\tat org.testng.internal.TestMethodWorker.run(TestMethodWorker.java:128)\r\n\tat java.base/java.util.ArrayList.forEach(ArrayList.java:1596)\r\n\tat org.testng.TestRunner.privateRun(TestRunner.java:794)\r\n\tat org.testng.TestRunner.run(TestRunner.java:596)\r\n\tat org.testng.SuiteRunner.runTest(SuiteRunner.java:377)\r\n\tat org.testng.SuiteRunner.runSequentially(SuiteRunner.java:371)\r\n\tat org.testng.SuiteRunner.privateRun(SuiteRunner.java:332)\r\n\tat org.testng.SuiteRunner.run(SuiteRunner.java:276)\r\n\tat org.testng.SuiteRunnerWorker.runSuite(SuiteRunnerWorker.java:53)\r\n\tat org.testng.SuiteRunnerWorker.run(SuiteRunnerWorker.java:96)\r\n\tat org.testng.TestNG.runSuitesSequentially(TestNG.java:1212)\r\n\tat org.testng.TestNG.runSuitesLocally(TestNG.java:1134)\r\n\tat org.testng.TestNG.runSuites(TestNG.java:1063)\r\n\tat org.testng.TestNG.run(TestNG.java:1031)\r\n\tat org.testng.remote.AbstractRemoteTestNG.run(AbstractRemoteTestNG.java:115)\r\n\tat org.testng.remote.RemoteTestNG.initAndRun(RemoteTestNG.java:293)\r\n\tat org.testng.remote.RemoteTestNG.main(RemoteTestNG.java:91)\r\n","duration":10612824300,"status":"failed"},"line":75,"name":"Navigate to the destination page by click on the destination menu","match":{"location":"sanity_script.step_defination.navigate_to_the_destination_page_by_click_on_the_destination_menu()"},"keyword":"Given "},{"result":{"status":"skipped"},"line":76,"name":"Goes to offline","match":{"location":"sanity_script.step_defination.goes_to_offline()"},"keyword":"When "},{"result":{"status":"skipped"},"line":77,"name":"single \"You are currently offline\" toast is displayed","match":{"arguments":[{"val":"\"You are currently offline\"","offset":7}],"location":"sanity_script.step_defination.single_toast_is_displayed(java.lang.String)"},"keyword":"Then "},{"result":{"status":"skipped"},"line":78,"name":"connect back to online","match":{"location":"sanity_script.step_defination.connect_back_to_online()"},"keyword":"When "},{"result":{"status":"skipped"},"line":79,"name":"single \"Connected\" toast is displayed","match":{"arguments":[{"val":"\"Connected\"","offset":7}],"location":"sanity_script.step_defination.single_toast_is_displayed(java.lang.String)"},"keyword":"Then "}],"tags":[{"name":"@tag"},{"name":"@offline"}]},{"start_timestamp":"2024-11-13T17:31:34.823Z","line":100,"name":"library page offline scenario","description":"","id":"title-of-your-feature;library-page-offline-scenario;;2","type":"scenario","keyword":"Scenario Outline","steps":[{"result":{"error_message":"org.openqa.selenium.NoSuchWindowException: no such window: target window already closed\nfrom unknown error: web view not found\n  (Session info: chrome=130.0.6723.117)\nBuild info: version: '4.26.0', revision: '8ccf0219d7'\nSystem info: os.name: 'Windows 11', os.arch: 'amd64', os.version: '10.0', java.version: '21.0.4'\nDriver info: org.openqa.selenium.chrome.ChromeDriver\nCommand: [fae04ea612c8201c3813ca8b7e822f07, findElement {using=xpath, value=//a[@href='/recordings']}]\nCapabilities {acceptInsecureCerts: false, browserName: chrome, browserVersion: 130.0.6723.117, chrome: {chromedriverVersion: 130.0.6723.116 (6ac35f94ae3..., userDataDir: C:\\Users\\guru\\AppData\\Local...}, fedcm:accounts: true, goog:chromeOptions: {debuggerAddress: localhost:52674}, networkConnectionEnabled: false, pageLoadStrategy: normal, platformName: windows, proxy: Proxy(), se:cdp: ws://localhost:52674/devtoo..., se:cdpVersion: 130.0.6723.117, setWindowRect: true, strictFileInteractability: false, timeouts: {implicit: 0, pageLoad: 300000, script: 30000}, unhandledPromptBehavior: dismiss and notify, webauthn:extension:credBlob: true, webauthn:extension:largeBlob: true, webauthn:extension:minPinLength: true, webauthn:extension:prf: true, webauthn:virtualAuthenticators: true}\nSession ID: fae04ea612c8201c3813ca8b7e822f07\r\n\tat java.base/jdk.internal.reflect.DirectConstructorHandleAccessor.newInstance(DirectConstructorHandleAccessor.java:62)\r\n\tat java.base/java.lang.reflect.Constructor.newInstanceWithCaller(Constructor.java:502)\r\n\tat java.base/java.lang.reflect.Constructor.newInstance(Constructor.java:486)\r\n\tat org.openqa.selenium.remote.ErrorCodec.decode(ErrorCodec.java:167)\r\n\tat org.openqa.selenium.remote.codec.w3c.W3CHttpResponseCodec.decode(W3CHttpResponseCodec.java:138)\r\n\tat org.openqa.selenium.remote.codec.w3c.W3CHttpResponseCodec.decode(W3CHttpResponseCodec.java:50)\r\n\tat org.openqa.selenium.remote.HttpCommandExecutor.execute(HttpCommandExecutor.java:190)\r\n\tat org.openqa.selenium.remote.service.DriverCommandExecutor.invokeExecute(DriverCommandExecutor.java:216)\r\n\tat org.openqa.selenium.remote.service.DriverCommandExecutor.execute(DriverCommandExecutor.java:174)\r\n\tat org.openqa.selenium.remote.RemoteWebDriver.execute(RemoteWebDriver.java:545)\r\n\tat org.openqa.selenium.remote.ElementLocation$ElementFinder$2.findElement(ElementLocation.java:165)\r\n\tat org.openqa.selenium.remote.ElementLocation.findElement(ElementLocation.java:59)\r\n\tat org.openqa.selenium.remote.RemoteWebDriver.findElement(RemoteWebDriver.java:368)\r\n\tat org.openqa.selenium.remote.RemoteWebDriver.findElement(RemoteWebDriver.java:362)\r\n\tat sanity_script.step_defination.navigate_to_the_library_page_by_clicking_on_the_library_menu(step_defination.java:113)\r\n\tat ✽.Navigate to the library page by clicking on the library menu(file:///C:/Users/guru/Desktop/Automation_script/OTF_script/src/main/java/feature_file/OTF_sanity.feature:87)\r\n","duration":4328200,"status":"failed"},"line":87,"name":"Navigate to the library page by clicking on the library menu","match":{"location":"sanity_script.step_defination.navigate_to_the_library_page_by_clicking_on_the_library_menu()"},"keyword":"Given "},{"result":{"status":"skipped"},"line":88,"name":"Goes to offline","match":{"location":"sanity_script.step_defination.goes_to_offline()"},"keyword":"When "},{"result":{"status":"skipped"},"line":89,"name":"single \"You are currently offline\" toast is displayed","match":{"arguments":[{"val":"\"You are currently offline\"","offset":7}],"location":"sanity_script.step_defination.single_toast_is_displayed(java.lang.String)"},"keyword":"Then "},{"result":{"status":"skipped"},"line":90,"name":"show stopper Ui with \"Something went wrong\" content is displayed","match":{"arguments":[{"val":"\"Something went wrong\"","offset":21}],"location":"sanity_script.step_defination.show_stopper_ui_with_content_is_displayed(java.lang.String)"},"keyword":"And "},{"result":{"status":"skipped"},"line":91,"name":"click on the Try again button","match":{"location":"sanity_script.step_defination.click_on_the_try_again_button()"},"keyword":"When "},{"result":{"status":"skipped"},"line":92,"name":"page should not reload and show stopper Ui is not removed","match":{"location":"sanity_script.step_defination.page_should_not_reload_and_show_stopper_ui_is_not_removed()"},"keyword":"Then "},{"result":{"status":"skipped"},"line":93,"name":"connect back to online","match":{"location":"sanity_script.step_defination.connect_back_to_online()"},"keyword":"When "},{"result":{"status":"skipped"},"line":94,"name":"single \"Connected\" toast is displayed","match":{"arguments":[{"val":"\"Connected\"","offset":7}],"location":"sanity_script.step_defination.single_toast_is_displayed(java.lang.String)"},"keyword":"Then "},{"result":{"duration":1010600,"status":"skipped"},"line":95,"name":"click on the Try again button","match":{"location":"sanity_script.step_defination.click_on_the_try_again_button()"},"keyword":"When "},{"result":{"status":"skipped"},"line":96,"name":"page should be loaded and showstopper ui should not be displayed","match":{"location":"sanity_script.step_defination.page_should_be_loaded_and_showstopper_ui_should_not_be_displayed()"},"keyword":"Then "}],"tags":[{"name":"@tag"},{"name":"@offline"}]},{"start_timestamp":"2024-11-13T17:31:34.836Z","line":116,"name":"Members page offline scenario","description":"","id":"title-of-your-feature;members-page-offline-scenario;;2","type":"scenario","keyword":"Scenario Outline","steps":[{"result":{"error_message":"org.openqa.selenium.TimeoutException: Expected condition failed: waiting for visibility of element located by By.xpath: //a[@href='/users'] (tried for 10 second(s) with 500 milliseconds interval)\r\n\tat org.openqa.selenium.support.ui.WebDriverWait.timeoutException(WebDriverWait.java:84)\r\n\tat org.openqa.selenium.support.ui.FluentWait.until(FluentWait.java:228)\r\n\tat sanity_script.step_defination.navigate_to_the_members_page_by_clicing_on_the_members_menu(step_defination.java:140)\r\n\tat ✽.Navigate to the Members page by clicing on the members menu(file:///C:/Users/guru/Desktop/Automation_script/OTF_script/src/main/java/feature_file/OTF_sanity.feature:104)\r\nCaused by: org.openqa.selenium.NoSuchWindowException: no such window: target window already closed\nfrom unknown error: web view not found\n  (Session info: chrome=130.0.6723.117)\nBuild info: version: '4.26.0', revision: '8ccf0219d7'\nSystem info: os.name: 'Windows 11', os.arch: 'amd64', os.version: '10.0', java.version: '21.0.4'\nDriver info: org.openqa.selenium.chrome.ChromeDriver\nCommand: [fae04ea612c8201c3813ca8b7e822f07, findElement {using=xpath, value=//a[@href='/users']}]\nCapabilities {acceptInsecureCerts: false, browserName: chrome, browserVersion: 130.0.6723.117, chrome: {chromedriverVersion: 130.0.6723.116 (6ac35f94ae3..., userDataDir: C:\\Users\\guru\\AppData\\Local...}, fedcm:accounts: true, goog:chromeOptions: {debuggerAddress: localhost:52674}, networkConnectionEnabled: false, pageLoadStrategy: normal, platformName: windows, proxy: Proxy(), se:cdp: ws://localhost:52674/devtoo..., se:cdpVersion: 130.0.6723.117, setWindowRect: true, strictFileInteractability: false, timeouts: {implicit: 0, pageLoad: 300000, script: 30000}, unhandledPromptBehavior: dismiss and notify, webauthn:extension:credBlob: true, webauthn:extension:largeBlob: true, webauthn:extension:minPinLength: true, webauthn:extension:prf: true, webauthn:virtualAuthenticators: true}\nSession ID: fae04ea612c8201c3813ca8b7e822f07\r\n\tat java.base/jdk.internal.reflect.DirectConstructorHandleAccessor.newInstance(DirectConstructorHandleAccessor.java:62)\r\n\tat java.base/java.lang.reflect.Constructor.newInstanceWithCaller(Constructor.java:502)\r\n\tat java.base/java.lang.reflect.Constructor.newInstance(Constructor.java:486)\r\n\tat org.openqa.selenium.remote.ErrorCodec.decode(ErrorCodec.java:167)\r\n\tat org.openqa.selenium.remote.codec.w3c.W3CHttpResponseCodec.decode(W3CHttpResponseCodec.java:138)\r\n\tat org.openqa.selenium.remote.codec.w3c.W3CHttpResponseCodec.decode(W3CHttpResponseCodec.java:50)\r\n\tat org.openqa.selenium.remote.HttpCommandExecutor.execute(HttpCommandExecutor.java:190)\r\n\tat org.openqa.selenium.remote.service.DriverCommandExecutor.invokeExecute(DriverCommandExecutor.java:216)\r\n\tat org.openqa.selenium.remote.service.DriverCommandExecutor.execute(DriverCommandExecutor.java:174)\r\n\tat org.openqa.selenium.remote.RemoteWebDriver.execute(RemoteWebDriver.java:545)\r\n\tat org.openqa.selenium.remote.ElementLocation$ElementFinder$2.findElement(ElementLocation.java:165)\r\n\tat org.openqa.selenium.remote.ElementLocation.findElement(ElementLocation.java:59)\r\n\tat org.openqa.selenium.remote.RemoteWebDriver.findElement(RemoteWebDriver.java:368)\r\n\tat org.openqa.selenium.remote.RemoteWebDriver.findElement(RemoteWebDriver.java:362)\r\n\tat org.openqa.selenium.support.ui.ExpectedConditions$7.apply(ExpectedConditions.java:194)\r\n\tat org.openqa.selenium.support.ui.ExpectedConditions$7.apply(ExpectedConditions.java:190)\r\n\tat org.openqa.selenium.support.ui.FluentWait.until(FluentWait.java:203)\r\n\tat sanity_script.step_defination.navigate_to_the_members_page_by_clicing_on_the_members_menu(step_defination.java:140)\r\n\tat java.base/jdk.internal.reflect.DirectMethodHandleAccessor.invoke(DirectMethodHandleAccessor.java:103)\r\n\tat java.base/java.lang.reflect.Method.invoke(Method.java:580)\r\n\tat io.cucumber.java.Invoker.doInvoke(Invoker.java:66)\r\n\tat io.cucumber.java.Invoker.invoke(Invoker.java:24)\r\n\tat io.cucumber.java.AbstractGlueDefinition.invokeMethod(AbstractGlueDefinition.java:47)\r\n\tat io.cucumber.java.JavaStepDefinition.execute(JavaStepDefinition.java:29)\r\n\tat io.cucumber.core.runner.CoreStepDefinition.execute(CoreStepDefinition.java:66)\r\n\tat io.cucumber.core.runner.PickleStepDefinitionMatch.runStep(PickleStepDefinitionMatch.java:62)\r\n\tat io.cucumber.core.runner.ExecutionMode$1.execute(ExecutionMode.java:10)\r\n\tat io.cucumber.core.runner.TestStep.executeStep(TestStep.java:81)\r\n\tat io.cucumber.core.runner.TestStep.run(TestStep.java:53)\r\n\tat io.cucumber.core.runner.PickleStepTestStep.run(PickleStepTestStep.java:51)\r\n\tat io.cucumber.core.runner.TestCase.run(TestCase.java:84)\r\n\tat io.cucumber.core.runner.Runner.runPickle(Runner.java:75)\r\n\tat io.cucumber.testng.TestNGCucumberRunner.lambda$runScenario$1(TestNGCucumberRunner.java:135)\r\n\tat io.cucumber.core.runtime.CucumberExecutionContext.lambda$runTestCase$5(CucumberExecutionContext.java:136)\r\n\tat io.cucumber.core.runtime.RethrowingThrowableCollector.executeAndThrow(RethrowingThrowableCollector.java:23)\r\n\tat io.cucumber.core.runtime.CucumberExecutionContext.runTestCase(CucumberExecutionContext.java:136)\r\n\tat io.cucumber.testng.TestNGCucumberRunner.runScenario(TestNGCucumberRunner.java:132)\r\n\tat io.cucumber.testng.AbstractTestNGCucumberTests.runScenario(AbstractTestNGCucumberTests.java:35)\r\n\tat java.base/jdk.internal.reflect.DirectMethodHandleAccessor.invoke(DirectMethodHandleAccessor.java:103)\r\n\tat java.base/java.lang.reflect.Method.invoke(Method.java:580)\r\n\tat org.testng.internal.MethodInvocationHelper.invokeMethod(MethodInvocationHelper.java:133)\r\n\tat org.testng.internal.TestInvoker.invokeMethod(TestInvoker.java:598)\r\n\tat org.testng.internal.TestInvoker.invokeTestMethod(TestInvoker.java:173)\r\n\tat org.testng.internal.MethodRunner.runInSequence(MethodRunner.java:46)\r\n\tat org.testng.internal.TestInvoker$MethodInvocationAgent.invoke(TestInvoker.java:824)\r\n\tat org.testng.internal.TestInvoker.invokeTestMethods(TestInvoker.java:146)\r\n\tat org.testng.internal.TestMethodWorker.invokeTestMethods(TestMethodWorker.java:146)\r\n\tat org.testng.internal.TestMethodWorker.run(TestMethodWorker.java:128)\r\n\tat java.base/java.util.ArrayList.forEach(ArrayList.java:1596)\r\n\tat org.testng.TestRunner.privateRun(TestRunner.java:794)\r\n\tat org.testng.TestRunner.run(TestRunner.java:596)\r\n\tat org.testng.SuiteRunner.runTest(SuiteRunner.java:377)\r\n\tat org.testng.SuiteRunner.runSequentially(SuiteRunner.java:371)\r\n\tat org.testng.SuiteRunner.privateRun(SuiteRunner.java:332)\r\n\tat org.testng.SuiteRunner.run(SuiteRunner.java:276)\r\n\tat org.testng.SuiteRunnerWorker.runSuite(SuiteRunnerWorker.java:53)\r\n\tat org.testng.SuiteRunnerWorker.run(SuiteRunnerWorker.java:96)\r\n\tat org.testng.TestNG.runSuitesSequentially(TestNG.java:1212)\r\n\tat org.testng.TestNG.runSuitesLocally(TestNG.java:1134)\r\n\tat org.testng.TestNG.runSuites(TestNG.java:1063)\r\n\tat org.testng.TestNG.run(TestNG.java:1031)\r\n\tat org.testng.remote.AbstractRemoteTestNG.run(AbstractRemoteTestNG.java:115)\r\n\tat org.testng.remote.RemoteTestNG.initAndRun(RemoteTestNG.java:293)\r\n\tat org.testng.remote.RemoteTestNG.main(RemoteTestNG.java:91)\r\n","duration":10297672700,"status":"failed"},"line":104,"name":"Navigate to the Members page by clicing on the members menu","match":{"location":"sanity_script.step_defination.navigate_to_the_members_page_by_clicing_on_the_members_menu()"},"keyword":"Given "},{"result":{"status":"skipped"},"line":105,"name":"Goes to offline","match":{"location":"sanity_script.step_defination.goes_to_offline()"},"keyword":"When "},{"result":{"status":"skipped"},"line":106,"name":"single \"You are currently offline\" toast is displayed","match":{"arguments":[{"val":"\"You are currently offline\"","offset":7}],"location":"sanity_script.step_defination.single_toast_is_displayed(java.lang.String)"},"keyword":"Then "},{"result":{"status":"skipped"},"line":111,"name":"connect back to online","match":{"location":"sanity_script.step_defination.connect_back_to_online()"},"keyword":"When "},{"result":{"status":"skipped"},"line":112,"name":"single \"Connected\" toast is displayed","match":{"arguments":[{"val":"\"Connected\"","offset":7}],"location":"sanity_script.step_defination.single_toast_is_displayed(java.lang.String)"},"keyword":"Then "}],"tags":[{"name":"@tag"},{"name":"@offline"}]},{"start_timestamp":"2024-11-13T17:31:45.168Z","line":133,"name":"Pre-preview page offline scenario","description":"","id":"title-of-your-feature;pre-preview-page-offline-scenario;;2","type":"scenario","keyword":"Scenario Outline","steps":[{"result":{"error_message":"org.openqa.selenium.NoSuchWindowException: no such window: target window already closed\nfrom unknown error: web view not found\n  (Session info: chrome=130.0.6723.117)\nBuild info: version: '4.26.0', revision: '8ccf0219d7'\nSystem info: os.name: 'Windows 11', os.arch: 'amd64', os.version: '10.0', java.version: '21.0.4'\nDriver info: org.openqa.selenium.chrome.ChromeDriver\nCommand: [fae04ea612c8201c3813ca8b7e822f07, get {url=https://onthefly-qa.contus.us/broadcast}]\nCapabilities {acceptInsecureCerts: false, browserName: chrome, browserVersion: 130.0.6723.117, chrome: {chromedriverVersion: 130.0.6723.116 (6ac35f94ae3..., userDataDir: C:\\Users\\guru\\AppData\\Local...}, fedcm:accounts: true, goog:chromeOptions: {debuggerAddress: localhost:52674}, networkConnectionEnabled: false, pageLoadStrategy: normal, platformName: windows, proxy: Proxy(), se:cdp: ws://localhost:52674/devtoo..., se:cdpVersion: 130.0.6723.117, setWindowRect: true, strictFileInteractability: false, timeouts: {implicit: 0, pageLoad: 300000, script: 30000}, unhandledPromptBehavior: dismiss and notify, webauthn:extension:credBlob: true, webauthn:extension:largeBlob: true, webauthn:extension:minPinLength: true, webauthn:extension:prf: true, webauthn:virtualAuthenticators: true}\nSession ID: fae04ea612c8201c3813ca8b7e822f07\r\n\tat java.base/jdk.internal.reflect.DirectConstructorHandleAccessor.newInstance(DirectConstructorHandleAccessor.java:62)\r\n\tat java.base/java.lang.reflect.Constructor.newInstanceWithCaller(Constructor.java:502)\r\n\tat java.base/java.lang.reflect.Constructor.newInstance(Constructor.java:486)\r\n\tat org.openqa.selenium.remote.ErrorCodec.decode(ErrorCodec.java:167)\r\n\tat org.openqa.selenium.remote.codec.w3c.W3CHttpResponseCodec.decode(W3CHttpResponseCodec.java:138)\r\n\tat org.openqa.selenium.remote.codec.w3c.W3CHttpResponseCodec.decode(W3CHttpResponseCodec.java:50)\r\n\tat org.openqa.selenium.remote.HttpCommandExecutor.execute(HttpCommandExecutor.java:190)\r\n\tat org.openqa.selenium.remote.service.DriverCommandExecutor.invokeExecute(DriverCommandExecutor.java:216)\r\n\tat org.openqa.selenium.remote.service.DriverCommandExecutor.execute(DriverCommandExecutor.java:174)\r\n\tat org.openqa.selenium.remote.RemoteWebDriver.execute(RemoteWebDriver.java:545)\r\n\tat org.openqa.selenium.remote.RemoteWebDriver.get(RemoteWebDriver.java:313)\r\n\tat sanity_script.method.stream_creation(method.java:15)\r\n\tat sanity_script.step_defination.navigate_to_pre_preview_screen(step_defination.java:146)\r\n\tat ✽.Navigate to pre-preview screen(file:///C:/Users/guru/Desktop/Automation_script/OTF_script/src/main/java/feature_file/OTF_sanity.feature:120)\r\n","duration":1999300,"status":"failed"},"line":120,"name":"Navigate to pre-preview screen","match":{"location":"sanity_script.step_defination.navigate_to_pre_preview_screen()"},"keyword":"Given "},{"result":{"status":"skipped"},"line":121,"name":"Goes to offline","match":{"location":"sanity_script.step_defination.goes_to_offline()"},"keyword":"When "},{"result":{"status":"skipped"},"line":122,"name":"single \"You are currently offline\" toast is displayed","match":{"arguments":[{"val":"\"You are currently offline\"","offset":7}],"location":"sanity_script.step_defination.single_toast_is_displayed(java.lang.String)"},"keyword":"Then "},{"result":{"status":"skipped"},"line":123,"name":"Click on the Enter stream button","match":{"location":"sanity_script.step_defination.click_on_the_enter_stream_button()"},"keyword":"When "},{"result":{"status":"skipped"},"line":124,"name":"Enter stream stream button should not be clickable","match":{"location":"sanity_script.step_defination.enter_stream_stream_button_should_not_be_clickable()"},"keyword":"Then "},{"result":{"status":"skipped"},"line":125,"name":"page is not navigating to the studio page","match":{},"keyword":"And "},{"result":{"status":"skipped"},"line":126,"name":"connect back to online","match":{"location":"sanity_script.step_defination.connect_back_to_online()"},"keyword":"When "},{"result":{"status":"skipped"},"line":127,"name":"single \"Connected\" toast is displayed","match":{"arguments":[{"val":"\"Connected\"","offset":7}],"location":"sanity_script.step_defination.single_toast_is_displayed(java.lang.String)"},"keyword":"Then "},{"result":{"status":"skipped"},"line":128,"name":"Click on the Enter stream button","match":{"location":"sanity_script.step_defination.click_on_the_enter_stream_button()"},"keyword":"When "},{"result":{"status":"skipped"},"line":129,"name":"page is navigating to the studio page","match":{"location":"sanity_script.step_defination.page_is_navigating_to_the_studio_page()"},"keyword":"Then "}],"tags":[{"name":"@tag"},{"name":"@offline"}]},{"start_timestamp":"2024-11-13T17:31:45.180Z","line":150,"name":"studio page offline scenario","description":"","id":"title-of-your-feature;studio-page-offline-scenario;;2","type":"scenario","keyword":"Scenario Outline","steps":[{"result":{"error_message":"org.openqa.selenium.NoSuchWindowException: no such window: target window already closed\nfrom unknown error: web view not found\n  (Session info: chrome=130.0.6723.117)\nBuild info: version: '4.26.0', revision: '8ccf0219d7'\nSystem info: os.name: 'Windows 11', os.arch: 'amd64', os.version: '10.0', java.version: '21.0.4'\nDriver info: org.openqa.selenium.chrome.ChromeDriver\nCommand: [fae04ea612c8201c3813ca8b7e822f07, findElement {using=xpath, value=//*[text()='Enter Stream']}]\nCapabilities {acceptInsecureCerts: false, browserName: chrome, browserVersion: 130.0.6723.117, chrome: {chromedriverVersion: 130.0.6723.116 (6ac35f94ae3..., userDataDir: C:\\Users\\guru\\AppData\\Local...}, fedcm:accounts: true, goog:chromeOptions: {debuggerAddress: localhost:52674}, networkConnectionEnabled: false, pageLoadStrategy: normal, platformName: windows, proxy: Proxy(), se:cdp: ws://localhost:52674/devtoo..., se:cdpVersion: 130.0.6723.117, setWindowRect: true, strictFileInteractability: false, timeouts: {implicit: 0, pageLoad: 300000, script: 30000}, unhandledPromptBehavior: dismiss and notify, webauthn:extension:credBlob: true, webauthn:extension:largeBlob: true, webauthn:extension:minPinLength: true, webauthn:extension:prf: true, webauthn:virtualAuthenticators: true}\nSession ID: fae04ea612c8201c3813ca8b7e822f07\r\n\tat java.base/jdk.internal.reflect.DirectConstructorHandleAccessor.newInstance(DirectConstructorHandleAccessor.java:62)\r\n\tat java.base/java.lang.reflect.Constructor.newInstanceWithCaller(Constructor.java:502)\r\n\tat java.base/java.lang.reflect.Constructor.newInstance(Constructor.java:486)\r\n\tat org.openqa.selenium.remote.ErrorCodec.decode(ErrorCodec.java:167)\r\n\tat org.openqa.selenium.remote.codec.w3c.W3CHttpResponseCodec.decode(W3CHttpResponseCodec.java:138)\r\n\tat org.openqa.selenium.remote.codec.w3c.W3CHttpResponseCodec.decode(W3CHttpResponseCodec.java:50)\r\n\tat org.openqa.selenium.remote.HttpCommandExecutor.execute(HttpCommandExecutor.java:190)\r\n\tat org.openqa.selenium.remote.service.DriverCommandExecutor.invokeExecute(DriverCommandExecutor.java:216)\r\n\tat org.openqa.selenium.remote.service.DriverCommandExecutor.execute(DriverCommandExecutor.java:174)\r\n\tat org.openqa.selenium.remote.RemoteWebDriver.execute(RemoteWebDriver.java:545)\r\n\tat org.openqa.selenium.remote.ElementLocation$ElementFinder$2.findElement(ElementLocation.java:165)\r\n\tat org.openqa.selenium.remote.ElementLocation.findElement(ElementLocation.java:59)\r\n\tat org.openqa.selenium.remote.RemoteWebDriver.findElement(RemoteWebDriver.java:368)\r\n\tat org.openqa.selenium.remote.RemoteWebDriver.findElement(RemoteWebDriver.java:362)\r\n\tat sanity_script.step_defination.navigate_to_the_studio_page(step_defination.java:174)\r\n\tat ✽.navigate to the studio page(file:///C:/Users/guru/Desktop/Automation_script/OTF_script/src/main/java/feature_file/OTF_sanity.feature:137)\r\n","duration":3157400,"status":"failed"},"line":137,"name":"navigate to the studio page","match":{"location":"sanity_script.step_defination.navigate_to_the_studio_page()"},"keyword":"Given "},{"result":{"status":"skipped"},"line":138,"name":"Goes to offline","match":{"location":"sanity_script.step_defination.goes_to_offline()"},"keyword":"When "},{"result":{"status":"skipped"},"line":139,"name":"single \"You are currently offline\" toast is displayed","match":{"arguments":[{"val":"\"You are currently offline\"","offset":7}],"location":"sanity_script.step_defination.single_toast_is_displayed(java.lang.String)"},"keyword":"Then "},{"result":{"status":"skipped"},"line":140,"name":"show stopper Ui with \"Something went wrong\" content is displayed","match":{"arguments":[{"val":"\"Something went wrong\"","offset":21}],"location":"sanity_script.step_defination.show_stopper_ui_with_content_is_displayed(java.lang.String)"},"keyword":"And "},{"result":{"status":"skipped"},"line":141,"name":"click on the Try again button","match":{"location":"sanity_script.step_defination.click_on_the_try_again_button()"},"keyword":"When "},{"result":{"status":"skipped"},"line":142,"name":"page should not reload and not navigate to the pre-preview screen","match":{"location":"sanity_script.step_defination.page_should_not_reload_and_not_navigate_to_the_pre_preview_screen()"},"keyword":"Then "},{"result":{"status":"skipped"},"line":143,"name":"connect back to online","match":{"location":"sanity_script.step_defination.connect_back_to_online()"},"keyword":"When "},{"result":{"status":"skipped"},"line":144,"name":"single \"Connected\" toast is displayed","match":{"arguments":[{"val":"\"Connected\"","offset":7}],"location":"sanity_script.step_defination.single_toast_is_displayed(java.lang.String)"},"keyword":"Then "},{"result":{"duration":998300,"status":"skipped"},"line":145,"name":"click on the Try again button","match":{"location":"sanity_script.step_defination.click_on_the_try_again_button()"},"keyword":"When "},{"result":{"status":"skipped"},"line":146,"name":"page should be loaded and navigated to the pre-preview screen","match":{"location":"sanity_script.step_defination.page_should_be_loaded_and_navigated_to_the_pre_preview_screen()"},"keyword":"Then "}],"tags":[{"name":"@tag"},{"name":"@offline"}]}],"name":"Title of your feature","description":"","id":"title-of-your-feature","keyword":"Feature","uri":"file:src/main/java/feature_file/OTF_sanity.feature","tags":[{"name":"@tag","type":"Tag","location":{"line":1,"column":1}}]}]